dpack/__init__.py
dpack/ape.py
dpack/dpack.py
dpack_py-0.2.2.dist-info/WHEEL
dpack_py-0.2.2.dist-info/METADATA
dpack_py-0.2.2.dist-info/RECORD
