Metadata-Version: 2.1
Name: dpack-py
Version: 0.2.2
Summary: dpack is an evm artifact package format
Author: banteg
Requires-Python: >=3.9
Classifier: License :: OSI Approved :: MIT License
Requires-Dist: pydantic >=2
Requires-Dist: httpx
Requires-Dist: ethpm-types
Requires-Dist: pytest ; extra == "dev"
Requires-Dist: ruff ; extra == "dev"
Requires-Dist: eth-ape ; extra == "dev"
Requires-Dist: ape-etherscan ; extra == "dev"
Requires-Dist: setuptools ; extra == "dev"
Requires-Dist: flit ; extra == "dev"
Provides-Extra: dev
